__init__.py
__version__.py
base.py
exceptions.py
lmdb.py
memory.py
serialize.py
util.py
stones-0.3.0.dist-info/LICENSE
stones-0.3.0.dist-info/METADATA
stones-0.3.0.dist-info/WHEEL
stones-0.3.0.dist-info/top_level.txt
stones-0.3.0.dist-info/RECORD
