Metadata-Version: 2.1
Name: stones
Version: 0.3.0
Summary: Library for Persistent key-value containers, compatible with Python dict
Author: Cristi Constantin
License: MIT License
Project-URL: Homepage, https://github.com/croqaz/Stones
Project-URL: Repository, https://github.com/croqaz/Stones
Classifier: Development Status :: 4 - Beta
Classifier: Environment :: Console
Classifier: Intended Audience :: Developers
Classifier: License :: OSI Approved :: MIT License
Classifier: Natural Language :: English
Classifier: Operating System :: OS Independent
Classifier: Programming Language :: Python :: 3 :: Only
Classifier: Topic :: Database
Classifier: Topic :: Software Development
Requires-Python: >=3.9
License-File: LICENSE
Provides-Extra: extra
Requires-Dist: lmdb ~=1.4 ; extra == 'extra'
Requires-Dist: ujson ~=5.8 ; extra == 'extra'
Requires-Dist: cbor2 ~=5.4 ; extra == 'extra'
Requires-Dist: msgpack ~=1.0 ; extra == 'extra'
Provides-Extra: test
Requires-Dist: pytest ~=7.4 ; extra == 'test'
Requires-Dist: pytest-cov ~=4.1 ; extra == 'test'
Requires-Dist: codecov ~=2.1 ; extra == 'test'
Requires-Dist: Flake8-pyproject ~=1.2 ; extra == 'test'
